Workbook

Sheet 使い方
A1: さつまいも栽培・収穫記録表（RRG）
A2: 作成日 | B2: 2026年9月29日
A4: ■ 入力のルール
A5: 黄色のセル・青字 | B5: ここに入力します
A6: 緑のセル・黒字 | B6: 自動で計算されます（入力しないでください）
A7: 収穫ID | B7: H-001 のように連番で振ります。貯蔵記録と販売記録はこのIDでつながります
A9: ■ シートの構成
A10: 畝マスター | B10: 畝ごとの品種・苗・定植日・日当たり。1回だけ入力します（A畝・B畝は植物管理シートの内容から転記済み）
A11: 収穫記録 | B11: 掘った日ごとに1行。収量・サイズ別本数・状態を記録します
A12: 貯蔵記録 | B12: 貯蔵中の温度・湿度・傷み・甘さを週1回程度記録します
A13: 販売記録 | B13: 売れた日ごとに1行。手数料・送料を差し引いた利益が自動計算されます
A14: 畝比較 | B14: A畝とB畝（苗の入手先・日当たりの違い）の結果を自動で比較します
A16: ■ サイズ規格（目安）
A17: 2L | B17: 1本 400g以上
A18: L | B18: 300〜400g
A19: M | B19: 200〜300g
A20: S | B20: 100〜200g
A21: 規格外 | B21: 100g未満、極端な変形、大きな割れ（加工用・自家用に回す）
A22: 注 | B22: 上記はRRGの暫定基準です。出荷先の規格があればそちらに合わせて変更してください
A24: ■ 収穫記録の記入例
A25: 例 | B25: H-001｜2026/10/05｜A畝｜掘った株数 10｜晴れ｜土：適湿｜総収量 8.5kg｜2L 3・L 8・M 12・S 6・規格外 4｜傷・割れ 2｜虫害 1｜病気の疑い 0｜形 4｜皮色 4
A27: ■ 収穫と貯蔵のポイント（一般的な目安）
A28: 収穫日 | B28: 晴れが2〜3日続き、土が乾いている日に掘る。雨の直後は傷みやすい
A29: 掘り方 | B29: 芋を傷つけないよう株元から離して掘る。傷は腐敗の入口になる
A30: 収穫直後 | B30: 洗わずに、土を軽く落として半日〜1日陰干しする
A31: 貯蔵 | B31: 適温は13〜15℃、湿度は85〜90%程度。10℃以下では低温障害で傷みやすく、高温では芽が出て消耗する
A32: 甘み | B32: 紅はるかは収穫後、数週間〜1か月ほど貯蔵すると甘みが増すとされる。販売は11月以降が有利
A34: ■ 法令・個人情報
A35: 種苗法 | B35: 紅はるかは登録品種の可能性が高い。芋（収穫物）の販売は可。苗やつる苗を増やして売らない
A36: 個人情報 | B36: 販売記録に購入者の氏名・住所は書かない（メルカリの取引画面で管理する）

Sheet 畝マスター
A1: 畝ID | B1: 品種 | C1: 苗の入手先 | D1: 苗本数 | E1: 定植日 | F1: 日当たり | G1: 土づくり・元肥 | H1: 追肥・管理 | I1: 備考
A2: A畝 | B2: 紅はるか | C2: 手島の苗（ネット購入） | E2: 46143 | F2: 良好 | I2: 植物管理シートより転記
A3: B畝 | B3: 紅はるか | C3: コメリ購入 | E3: 46143 | F3: やや不利 | I3: 植物管理シートより転記

Sheet 収穫記録
A1: 収穫ID | B1: 収穫日 | C1: 畝ID | D1: 品種 (自動) | E1: 定植日 (自動) | F1: 栽培日数 (自動) | G1: 掘った 株数 | H1: 天候 (当日) | I1: 土の状態 | J1: 総収量 (kg) | K1: 株あたり 収量kg (自動) | L1: 2L 本数 | M1: L 本数 | N1: M 本数 | O1: S 本数 | P1: 規格外 本数 | Q1: 合計本数 (自動) | R1: 平均重量 g/本 (自動) | S1: 傷・割れ 本数 | T1: 虫害 本数 | U1: 病気の 疑い本数 | V1: 良品率 (自動) | W1: 形の良さ 1〜5 | X1: 皮色 1〜5 | Y1: 写真URL | Z1: 備考
D2: =IF($C2="","",IFERROR(INDEX(畝マスター!$B$2:$B$21,MATCH($C2,畝マスター!$A$2:$A$21,0)),"")) | E2: =IF($C2="","",IFERROR(INDEX(畝マスター!$E$2:$E$21,MATCH($C2,畝マスター!$A$2:$A$21,0)),"")) | F2: =IF(OR($B2="",$E2=""),"",$B2-$E2) | K2: =IF(OR($J2="",N($G2)=0),"",$J2/$G2) | Q2: =IF(COUNT($L2:$P2)=0,"",SUM($L2:$P2)) | R2: =IF(OR($J2="",N($Q2)=0),"",$J2*1000/$Q2) | V2: =IF(N($Q2)=0,"",MAX(0,($Q2-$P2-SUM($S2:$U2)))/$Q2)
D3: =IF($C3="","",IFERROR(INDEX(畝マスター!$B$2:$B$21,MATCH($C3,畝マスター!$A$2:$A$21,0)),"")) | E3: =IF($C3="","",IFERROR(INDEX(畝マスター!$E$2:$E$21,MATCH($C3,畝マスター!$A$2:$A$21,0)),"")) | F3: =IF(OR($B3="",$E3=""),"",$B3-$E3) | K3: =IF(OR($J3="",N($G3)=0),"",$J3/$G3) | Q3: =IF(COUNT($L3:$P3)=0,"",SUM($L3:$P3)) | R3: =IF(OR($J3="",N($Q3)=0),"",$J3*1000/$Q3) | V3: =IF(N($Q3)=0,"",MAX(0,($Q3-$P3-SUM($S3:$U3)))/$Q3)
D4: =IF($C4="","",IFERROR(INDEX(畝マスター!$B$2:$B$21,MATCH($C4,畝マスター!$A$2:$A$21,0)),"")) | E4: =IF($C4="","",IFERROR(INDEX(畝マスター!$E$2:$E$21,MATCH($C4,畝マスター!$A$2:$A$21,0)),"")) | F4: =IF(OR($B4="",$E4=""),"",$B4-$E4) | K4: =IF(OR($J4="",N($G4)=0),"",$J4/$G4) | Q4: =IF(COUNT($L4:$P4)=0,"",SUM($L4:$P4)) | R4: =IF(OR($J4="",N($Q4)=0),"",$J4*1000/$Q4) | V4: =IF(N($Q4)=0,"",MAX(0,($Q4-$P4-SUM($S4:$U4)))/$Q4)
D5: =IF($C5="","",IFERROR(INDEX(畝マスター!$B$2:$B$21,MATCH($C5,畝マスター!$A$2:$A$21,0)),"")) | E5: =IF($C5="","",IFERROR(INDEX(畝マスター!$E$2:$E$21,MATCH($C5,畝マスター!$A$2:$A$21,0)),"")) | F5: =IF(OR($B5="",$E5=""),"",$B5-$E5) | K5: =IF(OR($J5="",N($G5)=0),"",$J5/$G5) | Q5: =IF(COUNT($L5:$P5)=0,"",SUM($L5:$P5)) | R5: =IF(OR($J5="",N($Q5)=0),"",$J5*1000/$Q5) | V5: =IF(N($Q5)=0,"",MAX(0,($Q5-$P5-SUM($S5:$U5)))/$Q5)
D6: =IF($C6="","",IFERROR(INDEX(畝マスター!$B$2:$B$21,MATCH($C6,畝マスター!$A$2:$A$21,0)),"")) | E6: =IF($C6="","",IFERROR(INDEX(畝マスター!$E$2:$E$21,MATCH($C6,畝マスター!$A$2:$A$21,0)),"")) | F6: =IF(OR($B6="",$E6=""),"",$B6-$E6) | K6: =IF(OR($J6="",N($G6)=0),"",$J6/$G6) | Q6: =IF(COUNT($L6:$P6)=0,"",SUM($L6:$P6)) | R6: =IF(OR($J6="",N($Q6)=0),"",$J6*1000/$Q6) | V6: =IF(N($Q6)=0,"",MAX(0,($Q6-$P6-SUM($S6:$U6)))/$Q6)
D7: =IF($C7="","",IFERROR(INDEX(畝マスター!$B$2:$B$21,MATCH($C7,畝マスター!$A$2:$A$21,0)),"")) | E7: =IF($C7="","",IFERROR(INDEX(畝マスター!$E$2:$E$21,MATCH($C7,畝マスター!$A$2:$A$21,0)),"")) | F7: =IF(OR($B7="",$E7=""),"",$B7-$E7) | K7: =IF(OR($J7="",N($G7)=0),"",$J7/$G7) | Q7: =IF(COUNT($L7:$P7)=0,"",SUM($L7:$P7)) | R7: =IF(OR($J7="",N($Q7)=0),"",$J7*1000/$Q7) | V7: =IF(N($Q7)=0,"",MAX(0,($Q7-$P7-SUM($S7:$U7)))/$Q7)
D8: =IF($C8="","",IFERROR(INDEX(畝マスター!$B$2:$B$21,MATCH($C8,畝マスター!$A$2:$A$21,0)),"")) | E8: =IF($C8="","",IFERROR(INDEX(畝マスター!$E$2:$E$21,MATCH($C8,畝マスター!$A$2:$A$21,0)),"")) | F8: =IF(OR($B8="",$E8=""),"",$B8-$E8) | K8: =IF(OR($J8="",N($G8)=0),"",$J8/$G8) | Q8: =IF(COUNT($L8:$P8)=0,"",SUM($L8:$P8)) | R8: =IF(OR($J8="",N($Q8)=0),"",$J8*1000/$Q8) | V8: =IF(N($Q8)=0,"",MAX(0,($Q8-$P8-SUM($S8:$U8)))/$Q8)
D9: =IF($C9="","",IFERROR(INDEX(畝マスター!$B$2:$B$21,MATCH($C9,畝マスター!$A$2:$A$21,0)),"")) | E9: =IF($C9="","",IFERROR(INDEX(畝マスター!$E$2:$E$21,MATCH($C9,畝マスター!$A$2:$A$21,0)),"")) | F9: =IF(OR($B9="",$E9=""),"",$B9-$E9) | K9: =IF(OR($J9="",N($G9)=0),"",$J9/$G9) | Q9: =IF(COUNT($L9:$P9)=0,"",SUM($L9:$P9)) | R9: =IF(OR($J9="",N($Q9)=0),"",$J9*1000/$Q9) | V9: =IF(N($Q9)=0,"",MAX(0,($Q9-$P9-SUM($S9:$U9)))/$Q9)
D10: =IF($C10="","",IFERROR(INDEX(畝マスター!$B$2:$B$21,MATCH($C10,畝マスター!$A$2:$A$21,0)),"")) | E10: =IF($C10="","",IFERROR(INDEX(畝マスター!$E$2:$E$21,MATCH($C10,畝マスター!$A$2:$A$21,0)),"")) | F10: =IF(OR($B10="",$E10=""),"",$B10-$E10) | K10: =IF(OR($J10="",N($G10)=0),"",$J10/$G10) | Q10: =IF(COUNT($L10:$P10)=0,"",SUM($L10:$P10)) | R10: =IF(OR($J10="",N($Q10)=0),"",$J10*1000/$Q10) | V10: =IF(N($Q10)=0,"",MAX(0,($Q10-$P10-SUM($S10:$U10)))/$Q10)
D11: =IF($C11="","",IFERROR(INDEX(畝マスター!$B$2:$B$21,MATCH($C11,畝マスター!$A$2:$A$21,0)),"")) | E11: =IF($C11="","",IFERROR(INDEX(畝マスター!$E$2:$E$21,MATCH($C11,畝マスター!$A$2:$A$21,0)),"")) | F11: =IF(OR($B11="",$E11=""),"",$B11-$E11) | K11: =IF(OR($J11="",N($G11)=0),"",$J11/$G11) | Q11: =IF(COUNT($L11:$P11)=0,"",SUM($L11:$P11)) | R11: =IF(OR($J11="",N($Q11)=0),"",$J11*1000/$Q11) | V11: =IF(N($Q11)=0,"",MAX(0,($Q11-$P11-SUM($S11:$U11)))/$Q11)
D12: =IF($C12="","",IFERROR(INDEX(畝マスター!$B$2:$B$21,MATCH($C12,畝マスター!$A$2:$A$21,0)),"")) | E12: =IF($C12="","",IFERROR(INDEX(畝マスター!$E$2:$E$21,MATCH($C12,畝マスター!$A$2:$A$21,0)),"")) | F12: =IF(OR($B12="",$E12=""),"",$B12-$E12) | K12: =IF(OR($J12="",N($G12)=0),"",$J12/$G12) | Q12: =IF(COUNT($L12:$P12)=0,"",SUM($L12:$P12)) | R12: =IF(OR($J12="",N($Q12)=0),"",$J12*1000/$Q12) | V12: =IF(N($Q12)=0,"",MAX(0,($Q12-$P12-SUM($S12:$U12)))/$Q12)
D13: =IF($C13="","",IFERROR(INDEX(畝マスター!$B$2:$B$21,MATCH($C13,畝マスター!$A$2:$A$21,0)),"")) | E13: =IF($C13="","",IFERROR(INDEX(畝マスター!$E$2:$E$21,MATCH($C13,畝マスター!$A$2:$A$21,0)),"")) | F13: =IF(OR($B13="",$E13=""),"",$B13-$E13) | K13: =IF(OR($J13="",N($G13)=0),"",$J13/$G13) | Q13: =IF(COUNT($L13:$P13)=0,"",SUM($L13:$P13)) | R13: =IF(OR($J13="",N($Q13)=0),"",$J13*1000/$Q13) | V13: =IF(N($Q13)=0,"",MAX(0,($Q13-$P13-SUM($S13:$U13)))/$Q13)
... D101: =IF($C101="","",IFERROR(INDEX(畝マスター!$B$2:$B$21,MATCH($C101,畝マスター!$A$2:$A$21,0)),"")) | E101: =IF($C101="","",IFERROR(INDEX(畝マスター!$E$2:$E$21,MATCH($C101,畝マスター!$A$2:$A$21,0)),"")) | F101: =IF(OR($B101="",$E101=""),"",$B101-$E101) | K101: =IF(OR($J101="",N($G101)=0),"",$J101/$G101) | Q101: =IF(COUNT($L101:$P101)=0,"",SUM($L101:$P101)) | R101: =IF(OR($J101="",N($Q101)=0),"",$J101*1000/$Q101) | V101: =IF(N($Q101)=0,"",MAX(0,($Q101-$P101-SUM($S101:$U101)))/$Q101)

Sheet 貯蔵記録
A1: 記録日 | B1: 収穫ID | C1: 収穫日 (自動) | D1: 経過日数 (自動) | E1: 保管場所 | F1: 温度 (℃) | G1: 湿度 (%) | H1: 残り本数 | I1: 腐敗・傷み 本数 | J1: 芽の有無 | K1: 甘さ評価 1〜5 | L1: 糖度Brix (測れれば) | M1: 食感 | N1: 状態メモ
C2: =IF($B2="","",IFERROR(INDEX(収穫記録!$B$2:$B$101,MATCH($B2,収穫記録!$A$2:$A$101,0)),"")) | D2: =IF(OR($A2="",$C2=""),"",$A2-$C2)
C3: =IF($B3="","",IFERROR(INDEX(収穫記録!$B$2:$B$101,MATCH($B3,収穫記録!$A$2:$A$101,0)),"")) | D3: =IF(OR($A3="",$C3=""),"",$A3-$C3)
C4: =IF($B4="","",IFERROR(INDEX(収穫記録!$B$2:$B$101,MATCH($B4,収穫記録!$A$2:$A$101,0)),"")) | D4: =IF(OR($A4="",$C4=""),"",$A4-$C4)
C5: =IF($B5="","",IFERROR(INDEX(収穫記録!$B$2:$B$101,MATCH($B5,収穫記録!$A$2:$A$101,0)),"")) | D5: =IF(OR($A5="",$C5=""),"",$A5-$C5)
C6: =IF($B6="","",IFERROR(INDEX(収穫記録!$B$2:$B$101,MATCH($B6,収穫記録!$A$2:$A$101,0)),"")) | D6: =IF(OR($A6="",$C6=""),"",$A6-$C6)
C7: =IF($B7="","",IFERROR(INDEX(収穫記録!$B$2:$B$101,MATCH($B7,収穫記録!$A$2:$A$101,0)),"")) | D7: =IF(OR($A7="",$C7=""),"",$A7-$C7)
C8: =IF($B8="","",IFERROR(INDEX(収穫記録!$B$2:$B$101,MATCH($B8,収穫記録!$A$2:$A$101,0)),"")) | D8: =IF(OR($A8="",$C8=""),"",$A8-$C8)
C9: =IF($B9="","",IFERROR(INDEX(収穫記録!$B$2:$B$101,MATCH($B9,収穫記録!$A$2:$A$101,0)),"")) | D9: =IF(OR($A9="",$C9=""),"",$A9-$C9)
C10: =IF($B10="","",IFERROR(INDEX(収穫記録!$B$2:$B$101,MATCH($B10,収穫記録!$A$2:$A$101,0)),"")) | D10: =IF(OR($A10="",$C10=""),"",$A10-$C10)
C11: =IF($B11="","",IFERROR(INDEX(収穫記録!$B$2:$B$101,MATCH($B11,収穫記録!$A$2:$A$101,0)),"")) | D11: =IF(OR($A11="",$C11=""),"",$A11-$C11)
C12: =IF($B12="","",IFERROR(INDEX(収穫記録!$B$2:$B$101,MATCH($B12,収穫記録!$A$2:$A$101,0)),"")) | D12: =IF(OR($A12="",$C12=""),"",$A12-$C12)
C13: =IF($B13="","",IFERROR(INDEX(収穫記録!$B$2:$B$101,MATCH($B13,収穫記録!$A$2:$A$101,0)),"")) | D13: =IF(OR($A13="",$C13=""),"",$A13-$C13)
... C101: =IF($B101="","",IFERROR(INDEX(収穫記録!$B$2:$B$101,MATCH($B101,収穫記録!$A$2:$A$101,0)),"")) | D101: =IF(OR($A101="",$C101=""),"",$A101-$C101)

Sheet 販売記録
A1: 販売日 | B1: 収穫ID | C1: 畝ID (自動) | D1: 販路 | E1: 商品形態 | F1: 規格 | G1: 重量 (kg) | H1: 販売価格 (円) | I1: 手数料率 | J1: 手数料 (円・自動) | K1: 送料 (円) | L1: 資材費 (円) | M1: 利益 (円・自動) | N1: kg単価 (円・自動) | O1: 購入者の評価 | P1: 備考
C2: =IF($B2="","",IFERROR(INDEX(収穫記録!$C$2:$C$101,MATCH($B2,収穫記録!$A$2:$A$101,0)),"")) | J2: =IF($H2="","",ROUNDDOWN($H2*N($I2),0)) | M2: =IF($H2="","",$H2-N($J2)-N($K2)-N($L2)) | N2: =IF(OR($H2="",N($G2)=0),"",$H2/$G2)
C3: =IF($B3="","",IFERROR(INDEX(収穫記録!$C$2:$C$101,MATCH($B3,収穫記録!$A$2:$A$101,0)),"")) | J3: =IF($H3="","",ROUNDDOWN($H3*N($I3),0)) | M3: =IF($H3="","",$H3-N($J3)-N($K3)-N($L3)) | N3: =IF(OR($H3="",N($G3)=0),"",$H3/$G3)
C4: =IF($B4="","",IFERROR(INDEX(収穫記録!$C$2:$C$101,MATCH($B4,収穫記録!$A$2:$A$101,0)),"")) | J4: =IF($H4="","",ROUNDDOWN($H4*N($I4),0)) | M4: =IF($H4="","",$H4-N($J4)-N($K4)-N($L4)) | N4: =IF(OR($H4="",N($G4)=0),"",$H4/$G4)
C5: =IF($B5="","",IFERROR(INDEX(収穫記録!$C$2:$C$101,MATCH($B5,収穫記録!$A$2:$A$101,0)),"")) | J5: =IF($H5="","",ROUNDDOWN($H5*N($I5),0)) | M5: =IF($H5="","",$H5-N($J5)-N($K5)-N($L5)) | N5: =IF(OR($H5="",N($G5)=0),"",$H5/$G5)
C6: =IF($B6="","",IFERROR(INDEX(収穫記録!$C$2:$C$101,MATCH($B6,収穫記録!$A$2:$A$101,0)),"")) | J6: =IF($H6="","",ROUNDDOWN($H6*N($I6),0)) | M6: =IF($H6="","",$H6-N($J6)-N($K6)-N($L6)) | N6: =IF(OR($H6="",N($G6)=0),"",$H6/$G6)
C7: =IF($B7="","",IFERROR(INDEX(収穫記録!$C$2:$C$101,MATCH($B7,収穫記録!$A$2:$A$101,0)),"")) | J7: =IF($H7="","",ROUNDDOWN($H7*N($I7),0)) | M7: =IF($H7="","",$H7-N($J7)-N($K7)-N($L7)) | N7: =IF(OR($H7="",N($G7)=0),"",$H7/$G7)
C8: =IF($B8="","",IFERROR(INDEX(収穫記録!$C$2:$C$101,MATCH($B8,収穫記録!$A$2:$A$101,0)),"")) | J8: =IF($H8="","",ROUNDDOWN($H8*N($I8),0)) | M8: =IF($H8="","",$H8-N($J8)-N($K8)-N($L8)) | N8: =IF(OR($H8="",N($G8)=0),"",$H8/$G8)
C9: =IF($B9="","",IFERROR(INDEX(収穫記録!$C$2:$C$101,MATCH($B9,収穫記録!$A$2:$A$101,0)),"")) | J9: =IF($H9="","",ROUNDDOWN($H9*N($I9),0)) | M9: =IF($H9="","",$H9-N($J9)-N($K9)-N($L9)) | N9: =IF(OR($H9="",N($G9)=0),"",$H9/$G9)
C10: =IF($B10="","",IFERROR(INDEX(収穫記録!$C$2:$C$101,MATCH($B10,収穫記録!$A$2:$A$101,0)),"")) | J10: =IF($H10="","",ROUNDDOWN($H10*N($I10),0)) | M10: =IF($H10="","",$H10-N($J10)-N($K10)-N($L10)) | N10: =IF(OR($H10="",N($G10)=0),"",$H10/$G10)
C11: =IF($B11="","",IFERROR(INDEX(収穫記録!$C$2:$C$101,MATCH($B11,収穫記録!$A$2:$A$101,0)),"")) | J11: =IF($H11="","",ROUNDDOWN($H11*N($I11),0)) | M11: =IF($H11="","",$H11-N($J11)-N($K11)-N($L11)) | N11: =IF(OR($H11="",N($G11)=0),"",$H11/$G11)
C12: =IF($B12="","",IFERROR(INDEX(収穫記録!$C$2:$C$101,MATCH($B12,収穫記録!$A$2:$A$101,0)),"")) | J12: =IF($H12="","",ROUNDDOWN($H12*N($I12),0)) | M12: =IF($H12="","",$H12-N($J12)-N($K12)-N($L12)) | N12: =IF(OR($H12="",N($G12)=0),"",$H12/$G12)
C13: =IF($B13="","",IFERROR(INDEX(収穫記録!$C$2:$C$101,MATCH($B13,収穫記録!$A$2:$A$101,0)),"")) | J13: =IF($H13="","",ROUNDDOWN($H13*N($I13),0)) | M13: =IF($H13="","",$H13-N($J13)-N($K13)-N($L13)) | N13: =IF(OR($H13="",N($G13)=0),"",$H13/$G13)
... C101: =IF($B101="","",IFERROR(INDEX(収穫記録!$C$2:$C$101,MATCH($B101,収穫記録!$A$2:$A$101,0)),"")) | J101: =IF($H101="","",ROUNDDOWN($H101*N($I101),0)) | M101: =IF($H101="","",$H101-N($J101)-N($K101)-N($L101)) | N101: =IF(OR($H101="",N($G101)=0),"",$H101/$G101)
A103: 手数料率の例：メルカリの販売手数料（現在の料率はメルカリの公式情報で確認して入力）。直売・知人は0%

Sheet 畝比較
A1: 畝比較（自動集計）
A2: A畝（ネット購入の苗・日当たり良好）とB畝（コメリの苗・日当たりやや不利）の違いを見るための表です
A4: 項目 | B4: A畝 | C4: B畝 | D4: 差（A−B）
A5: 掘った株数 | B5: =SUMIFS(収穫記録!$G$2:$G$101,収穫記録!$C$2:$C$101,B$4) | C5: =SUMIFS(収穫記録!$G$2:$G$101,収穫記録!$C$2:$C$101,C$4) | D5: =IF(OR(ISTEXT(B5),ISTEXT(C5)),"-",B5-C5)
A6: 総収量（kg） | B6: =SUMIFS(収穫記録!$J$2:$J$101,収穫記録!$C$2:$C$101,B$4) | C6: =SUMIFS(収穫記録!$J$2:$J$101,収穫記録!$C$2:$C$101,C$4) | D6: =IF(OR(ISTEXT(B6),ISTEXT(C6)),"-",B6-C6)
A7: 株あたり収量（kg） | B7: =IF(N(B5)=0,"-",B6/B5) | C7: =IF(N(C5)=0,"-",C6/C5) | D7: =IF(OR(ISTEXT(B7),ISTEXT(C7)),"-",B7-C7)
A8: 合計本数 | B8: =SUMIFS(収穫記録!$Q$2:$Q$101,収穫記録!$C$2:$C$101,B$4) | C8: =SUMIFS(収穫記録!$Q$2:$Q$101,収穫記録!$C$2:$C$101,C$4) | D8: =IF(OR(ISTEXT(B8),ISTEXT(C8)),"-",B8-C8)
A9: 平均重量（g/本） | B9: =IF(N(B8)=0,"-",B6*1000/B8) | C9: =IF(N(C8)=0,"-",C6*1000/C8) | D9: =IF(OR(ISTEXT(B9),ISTEXT(C9)),"-",B9-C9)
A10: 2L・L の割合 | B10: =IF(N(B8)=0,"-",(SUMIFS(収穫記録!$L$2:$L$101,収穫記録!$C$2:$C$101,B$4)+SUMIFS(収穫記録!$M$2:$M$101,収穫記録!$C$2:$C$101,B$4))/B8) | C10: =IF(N(C8)=0,"-",(SUMIFS(収穫記録!$L$2:$L$101,収穫記録!$C$2:$C$101,C$4)+SUMIFS(収穫記録!$M$2:$M$101,収穫記録!$C$2:$C$101,C$4))/C8) | D10: =IF(OR(ISTEXT(B10),ISTEXT(C10)),"-",B10-C10)
A11: 傷・割れ・虫害・病気 本数 | B11: =SUMIFS(収穫記録!$S$2:$S$101,収穫記録!$C$2:$C$101,B$4)+SUMIFS(収穫記録!$T$2:$T$101,収穫記録!$C$2:$C$101,B$4)+SUMIFS(収穫記録!$U$2:$U$101,収穫記録!$C$2:$C$101,B$4) | C11: =SUMIFS(収穫記録!$S$2:$S$101,収穫記録!$C$2:$C$101,C$4)+SUMIFS(収穫記録!$T$2:$T$101,収穫記録!$C$2:$C$101,C$4)+SUMIFS(収穫記録!$U$2:$U$101,収穫記録!$C$2:$C$101,C$4) | D11: =IF(OR(ISTEXT(B11),ISTEXT(C11)),"-",B11-C11)
A12: 良品率 | B12: =IF(N(B8)=0,"-",MAX(0,B8-SUMIFS(収穫記録!$P$2:$P$101,収穫記録!$C$2:$C$101,B$4)-B11)/B8) | C12: =IF(N(C8)=0,"-",MAX(0,C8-SUMIFS(収穫記録!$P$2:$P$101,収穫記録!$C$2:$C$101,C$4)-C11)/C8) | D12: =IF(OR(ISTEXT(B12),ISTEXT(C12)),"-",B12-C12)
A13: 売上（円） | B13: =SUMIFS(販売記録!$H$2:$H$101,販売記録!$C$2:$C$101,B$4) | C13: =SUMIFS(販売記録!$H$2:$H$101,販売記録!$C$2:$C$101,C$4) | D13: =IF(OR(ISTEXT(B13),ISTEXT(C13)),"-",B13-C13)
A14: 利益（円） | B14: =SUMIFS(販売記録!$M$2:$M$101,販売記録!$C$2:$C$101,B$4) | C14: =SUMIFS(販売記録!$M$2:$M$101,販売記録!$C$2:$C$101,C$4) | D14: =IF(OR(ISTEXT(B14),ISTEXT(C14)),"-",B14-C14)
A17: 読み方：A畝とB畝は苗の入手先と日当たりの2つが違うため、差が出てもどちらが原因かは切り分けられません。来年は条件を1つだけ変えると原因がわかります。
